{
  "settings": {
    "migrated": 6,
    "iconPacksPath": ".obsidian/icons",
    "fontSize": 16,
    "emojiStyle": "native",
    "iconColor": "#7c65ab",
    "recentlyUsedIcons": [
      "FabPython",
      "LiPenTool",
      "LiExcalidrawIcon",
      "LiFile",
      "LiSquareSigma"
    ],
    "recentlyUsedIconsSize": 5,
    "rules": [],
    "extraMargin": {
      "top": 0,
      "right": 4,
      "bottom": 0,
      "left": 0
    },
    "iconInTabsEnabled": true,
    "iconInTitleEnabled": false,
    "iconInTitlePosition": "above",
    "iconInFrontmatterEnabled": true,
    "iconInFrontmatterFieldName": "icon",
    "iconColorInFrontmatterFieldName": "iconColor",
    "iconsBackgroundCheckEnabled": false,
    "iconsInNotesEnabled": true,
    "iconsInLinksEnabled": true,
    "iconIdentifier": ":",
    "lucideIconPackType": "native",
    "debugMode": false,
    "useInternalPlugins": false
  },
  "Archived/Sem 4": "LiFolder",
  "Archived": "LiArchive",
  "Archived/Sem 4/control systems.md": "LiFile",
  "attachments": "LiImages",
  "Daily Notes": "LiFolders",
  "Excalidraw": "LiFolders",
  "Drawings": "LiFolder",
  "Programming": "LiFolders",
  "Templates": "LiFolder",
  "Upgrade": "LiFolder",
  "Upgrade/Bookmarks.md": "LiFile",
  "Upgrade/Goals.md": "LiFile",
  "Templates/Template, Daily Notes.md": "LiFile",
  "Programming/DSA": "LiFolder",
  "Programming/Dev": "LiFolder",
  "Programming/Computer Fundamentals": "LiFolder",
  "Daily Notes/2025": "LiFolders",
  "Programming/General Programming.md": "LiFile",
  "Programming/Projects.md": "LiFile",
  "Excalidraw/Scripts": "LiFolder",
  "Excalidraw/Scripts/Downloaded": "LiFolder",
  "Drawings/docker.excalidraw.md": "LiFile",
  "Drawings/System Design.excalidraw.md": "LiFile",
  "Daily Notes/2025/July": "LiFolder",
  "Daily Notes/2025/June": "LiFolder",
  "Daily Notes/2025/May": "LiFolder",
  "Archived/Sem 4/Digital Electronics.md": "LiFile",
  "Archived/Sem 4/Green Science.md": "LiFile",
  "Archived/Sem 4/IOT.md": "LiFile",
  "Archived/Sem 4/microprocessors.md": "LiFile",
  "Philosophia.md": "LiFile",
  "Upgrade/10x.md": "LiFile",
  "Upgrade/Hacks.md": "LiFile",
  "Upgrade/Motivation.md": "LiFile",
  "Upgrade/Learning.md": "LiFile",
  "Hackathons": "LiFolder",
  "Hackathons/Hackon.md": "LiFile",
  "Hackathons/Sparkathon.md": "LiFile",
  "Programming/Development.md": "LiFile",
  "Semester-5": "LiFolder",
  "Semester-5/Random Signal & Stochastic process.md": "LiFile",
  "Semester-5/VLSI Design (EC3102).md": "LiFile",
  "Semester-5/Analog Comm Sys.md": "LiFile",
  "Semester-5/Microcontroller & Embedded System (EC 3101).md": "LiFile",
  "Programming/Computer Fundamentals/OS": "LiFolder",
  "Programming/Android.md": "LiFile",
  "Programming/MLCC.md": "LiFile",
  "Maths.md": "LiSquareSigma",
  "Semester-5/EMT.md": "LiFile",
  "Programming/CP.md": "LiPenTool"
}